logfeed.py
setup.py
logfeed.egg-info/PKG-INFO
logfeed.egg-info/SOURCES.txt
logfeed.egg-info/dependency_links.txt
logfeed.egg-info/top_level.txt