Metadata-Version: 1.0
Name: logfeed
Version: 1.3
Summary: Read log messages from rotated files
Home-page: https://github.com/artyom/logfeed
Author: Artyom Pervukhin
Author-email: artyom@evasive.ru
License: UNKNOWN
Platform: UNKNOWN
